Metadata-Version: 2.4
Name: forked-jieba
Version: 20260128
Summary: Chinese Words Segmentation Utilities
Author-email: "Sun, Junyi" <ccnusjy@gmail.com>
License: MIT
Project-URL: Homepage, https://github.com/fxsjy/jieba
License-File: LICENSE
Dynamic: license-file
